ws_web_aiohttp/__init__.py
ws_web_aiohttp/connections.py
ws_web_aiohttp/db.py
ws_web_aiohttp/handlers.py
ws_web_aiohttp/server.py
ws_web_aiohttp/test.py
ws_web_aiohttp/test_support.py
ws_web_aiohttp/ws_web_aiohttp.service
ws_web_aiohttp/security/db.py
ws_web_aiohttp/security/db_auth.py
ws_web_aiohttp/security/handlers.py
ws_web_aiohttp/security/wrappers.py
ws_web_aiohttp/sql/__init__.py
ws_web_aiohttp/sql/init.sql
ws_web_aiohttp/static/__init__.py
ws_web_aiohttp/static/default.css
ws_web_aiohttp/static/default.js
ws_web_aiohttp/static/sheet.js
ws_web_aiohttp/templates/base.html
ws_web_aiohttp/templates/index.html
ws_web_aiohttp/templates/sheet.html
ws_web_aiohttp/templates/top_bar.html
ws_web_aiohttp/templates/user_index.html
ws_web_aiohttp/tests/__init__.py
ws_web_aiohttp/tests/database.py
ws_web_aiohttp/tests/tests.py
ws_web_aiohttp/tests/conf/deploy_console.py
ws_web_aiohttp/tests/conf/log.py
ws_web_aiohttp/tests/conf/simple.py
ws_web_aiohttp/tests/conf/simple_console.py
ws_web_aiohttp/tests/conf/simple_console_secure.py
ws_web_aiohttp/tests/conf/simple_secure.py
ws_web_aiohttp/tests/conf/web.py
ws_web_aiohttp/tests/conf/web_secure.py
ws_web_aiohttp-0.1a93.data/scripts/ws_web_aiohttp
ws_web_aiohttp-0.1a93.dist-info/DESCRIPTION.rst
ws_web_aiohttp-0.1a93.dist-info/METADATA
ws_web_aiohttp-0.1a93.dist-info/RECORD
ws_web_aiohttp-0.1a93.dist-info/WHEEL
ws_web_aiohttp-0.1a93.dist-info/metadata.json
ws_web_aiohttp-0.1a93.dist-info/top_level.txt
