Metadata-Version: 2.0
Name: ws-web-aiohttp
Version: 0.1a93
Summary: web server for web-sheets project
Home-page: http://github.com/chuck1/web_sheets
Author: Charles Rymal
Author-email: charlesrymal@gmail.com
License: MIT
Platform: UNKNOWN
Requires-Dist: Jinja2 (==2.9.6)
Requires-Dist: MarkupSafe (==1.0)
Requires-Dist: SQLAlchemy (==1.1.11)
Requires-Dist: aiohttp (==2.2.0)
Requires-Dist: aiohttp-security (==0.1.0)
Requires-Dist: aiohttp-session (==0.8.0)
Requires-Dist: aiopg (==0.13.0)
Requires-Dist: aioredis (==0.3.1)
Requires-Dist: appdirs (==1.4.3)
Requires-Dist: async-timeout (==1.2.1)
Requires-Dist: certifi (==2017.4.17)
Requires-Dist: chardet (==3.0.4)
Requires-Dist: codemach (==0.2)
Requires-Dist: fs (==2.0.4)
Requires-Dist: hiredis (==0.2.0)
Requires-Dist: idna (==2.5)
Requires-Dist: modconf (==0.3)
Requires-Dist: multidict (==2.1.6)
Requires-Dist: numpy (==1.13.0)
Requires-Dist: oauthlib (==2.0.2)
Requires-Dist: psycopg2 (==2.7.1)
Requires-Dist: pytz (==2017.2)
Requires-Dist: requests (==2.18.1)
Requires-Dist: requests-oauthlib (==0.8.0)
Requires-Dist: selenium (==3.4.3)
Requires-Dist: six (==1.10.0)
Requires-Dist: urllib3 (==1.21.1)
Requires-Dist: ws-callbacks (==0.2a0)
Requires-Dist: ws-sheets (==0.4.3b0)
Requires-Dist: ws-sheets-server (==0.4.1b0)
Requires-Dist: ws-storage (==0.5.1)
Requires-Dist: yarl (==0.10.3)
